DipTraceGenerator/Category.py
DipTraceGenerator/Component.py
DipTraceGenerator/ComponentLibrary.py
DipTraceGenerator/ComponentOrigin.py
DipTraceGenerator/ComponentShape.py
DipTraceGenerator/Dimension.py
DipTraceGenerator/Enums.py
DipTraceGenerator/Filename.py
DipTraceGenerator/Group.py
DipTraceGenerator/Hole.py
DipTraceGenerator/MainStack.py
DipTraceGenerator/MaskPaste.py
DipTraceGenerator/Mixins.py
DipTraceGenerator/Model3D.py
DipTraceGenerator/NameFont.py
DipTraceGenerator/Pad.py
DipTraceGenerator/PadStyle.py
DipTraceGenerator/Part.py
DipTraceGenerator/Pattern.py
DipTraceGenerator/PatternLibrary.py
DipTraceGenerator/PatternOrigin.py
DipTraceGenerator/PatternShape.py
DipTraceGenerator/Pin.py
DipTraceGenerator/Point.py
DipTraceGenerator/RecoveryCode.py
DipTraceGenerator/SpiceModel.py
DipTraceGenerator/Terminal.py
DipTraceGenerator/Utils.py
DipTraceGenerator/__init__.py
LICENSE
README.md
diptracegenerator-0.1.0.dist-info/LICENSE
diptracegenerator-0.1.0.dist-info/METADATA
diptracegenerator-0.1.0.dist-info/WHEEL
diptracegenerator-0.1.0.dist-info/entry_points.txt
diptracegenerator-0.1.0.dist-info/RECORD
